easy_ai18n/__init__.py
easy_ai18n/config.py
easy_ai18n/error.py
easy_ai18n/log.py
easy_ai18n/main.py
easy_ai18n/utils.py
easy_ai18n/core/__init__.py
easy_ai18n/core/builder.py
easy_ai18n/core/i18n.py
easy_ai18n/core/loader.py
easy_ai18n/core/parser.py
easy_ai18n/prompts/translate.py
easy_ai18n/translator/__init__.py
easy_ai18n/translator/base.py
easy_ai18n/translator/translator.py
easy_ai18n/translator/utils.py
easy_ai18n-1.1.1.dist-info/licenses/LICENSE
easy_ai18n-1.1.1.dist-info/METADATA
easy_ai18n-1.1.1.dist-info/WHEEL
easy_ai18n-1.1.1.dist-info/top_level.txt
easy_ai18n-1.1.1.dist-info/RECORD
