Metadata-Version: 2.4
Name: easy-ai18n
Version: 1.1.1
Summary: Simple and Elegant Python3 Internationalization (i18n) Tool
Author-email: 梓澪 <zilingmio@gmail.com>
License: MIT
Project-URL: Repository, https://github.com/z-mio/easy-ai18n
Project-URL: Issues, https://github.com/z-mio/easy-ai18n/issues
Requires-Python: >=3.12
License-File: LICENSE
Requires-Dist: googletrans
Requires-Dist: instructor
Requires-Dist: loguru
Requires-Dist: python-dotenv
Requires-Dist: pyyaml
Requires-Dist: tenacity
Requires-Dist: tqdm
Provides-Extra: dev
Requires-Dist: pytest>=8.4.2; extra == "dev"
Dynamic: license-file
